{
    "adid": null, 
    "name": "Zache Peluqueros", 
    "name_of_contact": "Zache Peluqueros", 
    "scrape_page": "https://www.bucmi.com/zachepeluqueros", 
    "business_website": "https://www.bucmi.com/zachepeluqueros", 
    "areas_covered": null, 
    "description": "Lo que verdaderamente importa es sentirse bien con uno mismo. En Zache Peluqueros nuestra intención principal es conseguirlo. Tenemos más de 15 años de experiencia en la peluquería y siempre disponemos de las últimas tendencias. Reserva online.", 
    "img_link": [
        "https://d1nd15w2k87kz0.cloudfront.net/Uploads/636023714357414875.jpg", 
        "https://d1nd15w2k87kz0.cloudfront.net/Uploads/636023714359446304.jpg", 
        "https://d1nd15w2k87kz0.cloudfront.net/Uploads/636023714361321723.jpg", 
        "https://d1nd15w2k87kz0.cloudfront.net/Uploads/636023714363509124.jpg", 
        "https://d1nd15w2k87kz0.cloudfront.net/Uploads/636023714363977907.jpg", 
        "https://d1nd15w2k87kz0.cloudfront.net/Uploads/636023714364915491.jpg"
    ], 
    "hqdb_featured_ad_type": "Featured", 
    "hqdb_nr_reviews": "1", 
    "hqdb_review_score": "8,0", 
    "accreditations": null, 
    "category": null, 
    "subcategory": null, 
    "street": "C/ Bubierca, 2", 
    "city": "Madrid", 
    "zipcode": "28018", 
    "formatted_address": "C/ Bubierca, 2, Madrid, 28018", 
    "country": "es", 
    "office_number": "914772737", 
    "office_number2": null, 
    "mobile_number": "671863366", 
    "mobile_number2": null, 
    "unidentified_phone_numbers": null, 
    "latitude": "40.3889951000", 
    "longitude": "-3.6633094000", 
    "business_email": null, 
    "yelp_page": null, 
    "facebook": null, 
    "twitter": null, 
    "instagram": null, 
    "venue_images": "https://d1nd15w2k87kz0.cloudfront.net/Logotipos/636023714775464402.jpg", 
    "opening_hours_raw": null, 
    "pricelist_link": null, 
    "services": [
        {
            "service_category": "Preferente", 
            "service": "Corte De Pelo Para Hombre", 
            "duration": 1800, 
            "price": "10,6 € ", 
            "description": "Ponte en manos de nuestros profesionales y consigue un look completamente personalizado. Ademas en nuestro centro te sentiras como en casa disfrutando del masaje que incluye el servicio. En Zache el corte de caballero incluye lavado con champu especifico."
        }, 
        {
            "service_category": "Preferente", 
            "service": "Corte De Pelo Para Mujer", 
            "duration": 1800, 
            "price": "13 € ", 
            "description": "¿Te apetece un cambio de look? Ponte en manos de nuestros profesionales que te asesoraran y te guiaran para que puedas elegir lo que mejor te siente. Luce un look a la moda ya!. El servicio incluye lavado, champu especifico con masaje. no incluye hidratacion ni peinado."
        }, 
        {
            "service_category": "Preferente", 
            "service": "Peinado Pelo Corto", 
            "duration": 1800, 
            "price": "11,7 € ", 
            "description": "Peinate y sientete guapa y estaras preparada para cualquier cita imprevista. Ven a Zache y ponte en manos de nuestros profesionales y te dejaremos lista solo en unos minutos.Consultar posible suplemento por aplicacion de hidratacion en el lavado"
        }, 
        {
            "service_category": "Peluquería", 
            "service": "Corte Peinado y Color", 
            "duration": 5400, 
            "price": "43 € ", 
            "description": "Ven a Zache, elige en nuestra amplia gama de colores de nuestra carta. Ponte en manos de nuestros profesionales que te guiaran en la eleccion y conseguiras lucir una cabello luminoso y cuidado. El servicio incluye lavado con hidratacion, servicio de color, peinado y productos de acabado."
        }, 
        {
            "service_category": "Peluquería", 
            "service": "Peinado Pelo Largo", 
            "duration": 2700, 
            "price": "13 € ", 
            "description": "¡Luce una melena cuidada y brillante recien peinada! lista para cualquier evento que te pueda surgir.el seervicio incluye lavado y peinado. Consultar posible suplemento por aplicacion de hidratacion en el lavado."
        }, 
        {
            "service_category": "Peluquería", 
            "service": "Peinado y Color", 
            "duration": 3600, 
            "price": "32,5 € ", 
            "description": "En Zache te preparamos para cualquier momento y te asesoramos como mereces, según tu estilo. Elige unas ondas o una melena suave y lisa ¡Tu decides! Sera tu manera de culminar el servicio de coloracion en el que pondremos a tu disposicion nuestra carta de colores. El servicio incluye lavado con hidratacion, coloracion, peinado y producto de acabado."
        }, 
        {
            "service_category": "Peluquería", 
            "service": "Taninoplastia", 
            "duration": 7200, 
            "price": "130 € ", 
            "description": "Ven a Zache y dia adios a los rizos por unos meses. Gracias al producto completamente natural sin formoles ni acidos que usamos en nuestro centro, conseguiras un resultado duradero sin dañar tu pelo. Pruebalo y no te arrepentiras."
        }, 
        {
            "service_category": "Peluquería", 
            "service": "Corte De Pelo Para Hombre", 
            "duration": 1800, 
            "price": "10,6 € ", 
            "description": "Ponte en manos de nuestros profesionales y consigue un look completamente personalizado. Ademas en nuestro centro te sentiras como en casa disfrutando del masaje que incluye el servicio. En Zache el corte de caballero incluye lavado con champu especifico."
        }, 
        {
            "service_category": "Peluquería", 
            "service": "Corte De Pelo Para Mujer", 
            "duration": 1800, 
            "price": "13 € ", 
            "description": "¿Te apetece un cambio de look? Ponte en manos de nuestros profesionales que te asesoraran y te guiaran para que puedas elegir lo que mejor te siente. Luce un look a la moda ya!. El servicio incluye lavado, champu especifico con masaje. no incluye hidratacion ni peinado."
        }, 
        {
            "service_category": "Peluquería", 
            "service": "Peinado Pelo Corto", 
            "duration": 1800, 
            "price": "11,7 € ", 
            "description": "Peinate y sientete guapa y estaras preparada para cualquier cita imprevista. Ven a Zache y ponte en manos de nuestros profesionales y te dejaremos lista solo en unos minutos.Consultar posible suplemento por aplicacion de hidratacion en el lavado"
        }, 
        {
            "service_category": "Manicura y Pedicura", 
            "service": "Corte Peinado y Color", 
            "duration": 5400, 
            "price": "43 € ", 
            "description": "Ven a Zache, elige en nuestra amplia gama de colores de nuestra carta. Ponte en manos de nuestros profesionales que te guiaran en la eleccion y conseguiras lucir una cabello luminoso y cuidado. El servicio incluye lavado con hidratacion, servicio de color, peinado y productos de acabado."
        }
    ]
}