{
    "adid": null, 
    "name": "Paco Gutierrez", 
    "name_of_contact": "Paco Gutierrez", 
    "scrape_page": "https://www.bucmi.com/pacogutierrez", 
    "business_website": "https://www.bucmi.com/pacogutierrez", 
    "areas_covered": null, 
    "description": "Es un salón que nació hace tres años en el barrio “Bola de Oro” de Granada, con la idea de cubrir las necesidades de los vecinos de la zona, creando un tándem perfecto con la experiencia, fuerza y creatividad de cada uno de sus profesionales.Te esperamos", 
    "img_link": null, 
    "hqdb_featured_ad_type": "Featured", 
    "hqdb_nr_reviews": "2", 
    "hqdb_review_score": "6,0", 
    "accreditations": null, 
    "category": null, 
    "subcategory": null, 
    "street": "C/ Duende, 5", 
    "city": "Granada", 
    "zipcode": "18008", 
    "formatted_address": "C/ Duende, 5, Granada, 18008", 
    "country": "es", 
    "office_number": "958058653", 
    "office_number2": null, 
    "mobile_number": "635211461", 
    "mobile_number2": null, 
    "unidentified_phone_numbers": null, 
    "latitude": "37.1538899000", 
    "longitude": "-3.5706099999", 
    "business_email": null, 
    "yelp_page": null, 
    "facebook": null, 
    "twitter": null, 
    "instagram": null, 
    "venue_images": "https://d1nd15w2k87kz0.cloudfront.net/Logotipos/635810741261972408.jpg", 
    "opening_hours_raw": null, 
    "pricelist_link": null, 
    "services": [
        {
            "service_category": "Preferente", 
            "service": "Color, Cortar Y Peinar", 
            "duration": 3600, 
            "price": "36 € ", 
            "description": "Pack para mantener el pelo bonito y sano. El servicio incluye lavado previo, color, corte de moda y peinado final. Si tienes alguna duda, consulta con nuestros profesionales."
        }, 
        {
            "service_category": "Preferente", 
            "service": "Higiene Facial", 
            "duration": 5400, 
            "price": "30 € ", 
            "description": "Cuida la piel de tu rostro con una higiene facial. Su objetivo es limpiar en profundidad células muertas y espinillas y tonificar los músculos de la cara mediante el masaje facial."
        }, 
        {
            "service_category": "Preferente", 
            "service": "Manicura Shellac", 
            "duration": 2700, 
            "price": "20 € ", 
            "description": "Disfruta de una manicura perfecta. El tratamiento incluye la preparación y tratamiento de las uñas, con posterior esmaltado de larga duración utilizando la marca Shellac."
        }, 
        {
            "service_category": "Peluquería", 
            "service": "Color, Cortar Y Peinar", 
            "duration": 3600, 
            "price": "36 € ", 
            "description": "Pack para mantener el pelo bonito y sano. El servicio incluye lavado previo, color, corte de moda y peinado final. Si tienes alguna duda, consulta con nuestros profesionales."
        }, 
        {
            "service_category": "Estética", 
            "service": "Color, Cortar Y Peinar", 
            "duration": 3600, 
            "price": "36 € ", 
            "description": "Pack para mantener el pelo bonito y sano. El servicio incluye lavado previo, color, corte de moda y peinado final. Si tienes alguna duda, consulta con nuestros profesionales."
        }, 
        {
            "service_category": "Manicura y Pedicura", 
            "service": "Color, Cortar Y Peinar", 
            "duration": 3600, 
            "price": "36 € ", 
            "description": "Pack para mantener el pelo bonito y sano. El servicio incluye lavado previo, color, corte de moda y peinado final. Si tienes alguna duda, consulta con nuestros profesionales."
        }
    ]
}