{
    "adid": null, 
    "name": "Clinica Massana Lopez Gomez", 
    "name_of_contact": "Clinica Massana Lopez Gomez", 
    "scrape_page": "https://www.bucmi.com/massanalopezgomez", 
    "business_website": "https://www.bucmi.com/massanalopezgomez", 
    "areas_covered": null, 
    "description": "En las clínicas de estética Massana de Valladolid podrás encontar la plataforma láser más moderna más demandada por hombres y mujeres. Donde contamos con médicos y dermatólogos a tu disposición para lo que necesites.", 
    "img_link": [
        "https://d1nd15w2k87kz0.cloudfront.net/Uploads/635600394577987481.jpg", 
        "https://d1nd15w2k87kz0.cloudfront.net/Uploads/635924260354372633.jpg", 
        "https://d1nd15w2k87kz0.cloudfront.net/Uploads/635924260698601231.jpg", 
        "https://d1nd15w2k87kz0.cloudfront.net/Uploads/635924260822042394.jpg", 
        "https://d1nd15w2k87kz0.cloudfront.net/Uploads/635924260963922730.jpg", 
        "https://d1nd15w2k87kz0.cloudfront.net/Uploads/635924261146602064.jpg", 
        "https://d1nd15w2k87kz0.cloudfront.net/Uploads/635924261279411547.jpg"
    ], 
    "hqdb_featured_ad_type": "Featured", 
    "hqdb_nr_reviews": "1", 
    "hqdb_review_score": "9,0", 
    "accreditations": null, 
    "category": null, 
    "subcategory": null, 
    "street": "C/ Carbonero, 7", 
    "city": "Valladolid", 
    "zipcode": "47002", 
    "formatted_address": "C/ Carbonero, 7, Valladolid, 47002", 
    "country": "es", 
    "office_number": "983217850", 
    "office_number2": null, 
    "mobile_number": "647681387", 
    "mobile_number2": null, 
    "unidentified_phone_numbers": null, 
    "latitude": "41.6497805000", 
    "longitude": "-4.7239730000", 
    "business_email": null, 
    "yelp_page": null, 
    "facebook": null, 
    "twitter": null, 
    "instagram": null, 
    "venue_images": "https://d1nd15w2k87kz0.cloudfront.net/Logotipos/635961635217440638.jpg", 
    "opening_hours_raw": null, 
    "pricelist_link": null, 
    "services": [
        {
            "service_category": "Preferente", 
            "service": "Tratamiento Rejuvenicimiento Facial", 
            "duration": 3600, 
            "price": "58 € ", 
            "description": "Consigue una piel más joven gracias a nuestro completo tratamiento de rejuvenicimiento facial sin cirugía. Consiste en un completo cóctel de vitaminas que atenúa las arrugas, elimina las manchas, quita las marcas de acné y mejora la elasticidad. Haz ya tu reserva con Bucmi.com."
        }, 
        {
            "service_category": "Preferente", 
            "service": "Tratamiento Facial De Lujo", 
            "duration": 2700, 
            "price": "36 € ", 
            "description": "El elixir de juventud en forma de un tratamiento facial iluminante. Incluye: Diagnóstico facial , Pulverizado purificante con microcristales de corindón, Radiofrecuencia (ideal para personas con flacidez) y ampolla flash colágeno."
        }, 
        {
            "service_category": "Preferente", 
            "service": "Tratamiento Facial Antimanchas", 
            "duration": 2700, 
            "price": "36 € ", 
            "description": "Di adiós a las manchas con el mejor tratamiento médico. Descubre los efectos despigmentantes del laser fraccionado resurfacing. Incluye: Diagnóstico de la piel + Higiene + Sesión láser fraccionado Resurfacing + Mascarilla de colágeno + elastina."
        }, 
        {
            "service_category": "Estética", 
            "service": "Tratamiento Rejuvenicimiento Facial", 
            "duration": 3600, 
            "price": "58 € ", 
            "description": "Consigue una piel más joven gracias a nuestro completo tratamiento de rejuvenicimiento facial sin cirugía. Consiste en un completo cóctel de vitaminas que atenúa las arrugas, elimina las manchas, quita las marcas de acné y mejora la elasticidad. Haz ya tu reserva con Bucmi.com."
        }, 
        {
            "service_category": "Estética", 
            "service": "Mesoterapia Corporal", 
            "duration": 900, 
            "price": "49 € ", 
            "description": "Combate la celulitis y la grasa localizada tratando el edema intersticial y el estrangulamiento de los adipocitos mediante la reestructuración de las fibras de colágeno del tejido conjuntivo. Es un método inyectable por vía subcutánea poco invasivo."
        }, 
        {
            "service_category": "Estética", 
            "service": "Tratamiento Facial De Lujo", 
            "duration": 2700, 
            "price": "36 € ", 
            "description": "El elixir de juventud en forma de un tratamiento facial iluminante. Incluye: Diagnóstico facial , Pulverizado purificante con microcristales de corindón, Radiofrecuencia (ideal para personas con flacidez) y ampolla flash colágeno."
        }, 
        {
            "service_category": "Estética", 
            "service": "Tratamiento Facial Antimanchas", 
            "duration": 2700, 
            "price": "36 € ", 
            "description": "Di adiós a las manchas con el mejor tratamiento médico. Descubre los efectos despigmentantes del laser fraccionado resurfacing. Incluye: Diagnóstico de la piel + Higiene + Sesión láser fraccionado Resurfacing + Mascarilla de colágeno + elastina."
        }, 
        {
            "service_category": "Depilación", 
            "service": "Tratamiento Rejuvenicimiento Facial", 
            "duration": 3600, 
            "price": "58 € ", 
            "description": "Consigue una piel más joven gracias a nuestro completo tratamiento de rejuvenicimiento facial sin cirugía. Consiste en un completo cóctel de vitaminas que atenúa las arrugas, elimina las manchas, quita las marcas de acné y mejora la elasticidad. Haz ya tu reserva con Bucmi.com."
        }, 
        {
            "service_category": "Depilación", 
            "service": "Mesoterapia Corporal", 
            "duration": 900, 
            "price": "49 € ", 
            "description": "Combate la celulitis y la grasa localizada tratando el edema intersticial y el estrangulamiento de los adipocitos mediante la reestructuración de las fibras de colágeno del tejido conjuntivo. Es un método inyectable por vía subcutánea poco invasivo."
        }, 
        {
            "service_category": "Depilación", 
            "service": "Tratamiento Facial De Lujo", 
            "duration": 2700, 
            "price": "36 € ", 
            "description": "El elixir de juventud en forma de un tratamiento facial iluminante. Incluye: Diagnóstico facial , Pulverizado purificante con microcristales de corindón, Radiofrecuencia (ideal para personas con flacidez) y ampolla flash colágeno."
        }
    ]
}